MANIFEST.in
README.md
setup.py
pwn_machine.egg-info/PKG-INFO
pwn_machine.egg-info/SOURCES.txt
pwn_machine.egg-info/dependency_links.txt
pwn_machine.egg-info/entry_points.txt
pwn_machine.egg-info/requires.txt
pwn_machine.egg-info/top_level.txt
pwnmachine/__init__.py
pwnmachine/cli.py
pwnmachine/install.py
pwnmachine/version.txt
pwnmachine/PwnMachine/Config.py
pwnmachine/PwnMachine/Pipeline.py
pwnmachine/PwnMachine/PwnMachine.py
pwnmachine/PwnMachine/__init__.py
pwnmachine/PwnMachine/traefik.py
pwnmachine/PwnMachine/utils.py
pwnmachine/cli/container.py
pwnmachine/cli/dns.py
pwnmachine/cli/pipeline.py.disable
pwnmachine/cli/service.py
pwnmachine/cli/volume.py
pwnmachine/skel/services/dns/Dockerfile
pwnmachine/skel/services/dns/docker-compose.yml
pwnmachine/skel/services/dns/domain.sql.tpl
pwnmachine/skel/services/dns/pdns.conf.tpl
pwnmachine/skel/services/dns/start.sh
pwnmachine/skel/services/traefik/docker-compose.yml
pwnmachine/skel/services/web/Dockerfile
pwnmachine/skel/services/web/dirlist.tpl
pwnmachine/skel/services/web/docker-compose.yml
pwnmachine/skel/services/web/handle_php.conf
pwnmachine/skel/services/web/www.tpl