Metadata-Version: 2.1
Name: pwn-machine
Version: 1.1.2
Summary: Simple self hosting solution based on docker for bug hunters.
Home-page: https://github.com/yeswehack/pwn-machine
Author: @BitK_
Author-email: bitk@yeswehack.com
License: UNKNOWN
Platform: UNKNOWN
